taskthread
