Metadata-Version: 1.0
Name: taskthread
Version: 1.4
Summary: Simple thread module to repetitively perform a task on a single thread
Home-page: http://hpcloud.com
Author: John Herndon
Author-email: john.herndon@hp.com
License: Apache
Platform: UNKNOWN
